beancount_format/__init__.py
beancount_format/beancount_format.abi3.so
beancount_format/beancount_format.pyi
beancount_format/py.typed
beancount_format-0.1.21.dist-info/METADATA
beancount_format-0.1.21.dist-info/WHEEL
beancount_format-0.1.21.dist-info/entry_points.txt
beancount_format-0.1.21.dist-info/licenses/LICENSE
beancount_format-0.1.21.dist-info/RECORD
