Metadata-Version: 2.4
Name: beancount-format
Version: 0.1.21
Classifier: Programming Language :: Rust
Classifier: Programming Language :: Python
Classifier: Programming Language :: Python :: 3
Classifier: Programming Language :: Python :: 3 :: Only
Classifier: License :: OSI Approved :: MIT License
License-File: LICENSE
Summary: Beancount formatter powered by dprint-plugin-beancount
Home-Page: https://github.com/trim21/beancount-format
Author-email: trim21 <trim21.me@gmail.com>
Requires-Python: >=3.10
